rackio_socket/__init__.py
rackio_socket/_singleton.py
rackio_socket/core.py
rackio_socket/decorator.py
rackio_socket/worker.py
rackio_socket/events/__init__.py
rackio_socket/events/alarms.py
rackio_socket/events/comm.py
rackio_socket/events/controls.py
rackio_socket/events/events.py
rackio_socket/events/tags.py
RackioSocket-0.9.dist-info/LICENSE
RackioSocket-0.9.dist-info/METADATA
RackioSocket-0.9.dist-info/WHEEL
RackioSocket-0.9.dist-info/top_level.txt
RackioSocket-0.9.dist-info/RECORD
