Metadata-Version: 2.1
Name: RackioSocket
Version: 0.9
Summary: A Rackio extension to add a SocketIO Server to Rackio
Home-page: https://github.com/rack-io/rackio-socket
Author: Nelson Carrasquel
Author-email: rackio.framework@outlook.com
License: MIT
Platform: UNKNOWN
Classifier: Programming Language :: Python :: 3
Classifier: License :: OSI Approved :: MIT License
Classifier: Operating System :: OS Independent
Requires-Dist: eventlet
Requires-Dist: python-socketio
Requires-Dist: gevent
Requires-Dist: gevent-websocket
